phyllo/__init__.py
phyllo/io/__init__.py
phyllo/io/cli/__init__.py
phyllo/io/cli/stdin.py
phyllo/io/cli/args/__init__.py
phyllo/io/cli/args/args.py
phyllo/io/cli/args/protocol.py
phyllo/io/interfaces/__init__.py
phyllo/io/interfaces/serial.py
phyllo/io/polling/__init__.py
phyllo/io/polling/serial.py
phyllo/io/polling/stack.py
phyllo/io/threading/__init__.py
phyllo/io/threading/links.py
phyllo/io/threading/primitives.py
phyllo/io/threading/serial.py
phyllo/io/tui/__init__.py
phyllo/io/tui/console.py
phyllo/protocol/__init__.py
phyllo/protocol/communication.py
phyllo/protocol/stacks.py
phyllo/protocol/application/__init__.py
phyllo/protocol/application/endpoints.py
phyllo/protocol/application/pubsub.py
phyllo/protocol/application/stacks.py
phyllo/protocol/presentation/__init__.py
phyllo/protocol/presentation/documents.py
phyllo/protocol/transport/__init__.py
phyllo/protocol/transport/datagrams.py
phyllo/protocol/transport/frames.py
phyllo/protocol/transport/reliablebuffers.py
phyllo/protocol/transport/stacks.py
tests/__init__.py
tests/io/__init__.py
tests/io/interfaces/__init__.py
tests/io/interfaces/serial/__init__.py
tests/io/interfaces/serial/console_stream.py
tests/io/interfaces/serial/list.py
tests/io/interfaces/serial/reader.py
tests/io/interfaces/serial/receiver.py
tests/io/polling/__init__.py
tests/io/polling/loopback.py
tests/io/polling/serial/__init__.py
tests/io/polling/serial/console.py
tests/io/polling/serial/echo.py
tests/io/polling/serial/echo_performance.py
tests/io/polling/serial/endpoints_console.py
tests/io/polling/serial/receiver.py
tests/io/threading/__init__.py
tests/io/threading/serial/__init__.py
tests/io/threading/serial/console.py
tests/io/threading/serial/echo.py
tests/io/threading/serial/echo_performance.py
tests/io/threading/serial/endpoints_console.py
tests/io/threading/serial/receiver.py
tests/unit/__init__.py
tests/unit/io/__init__.py
tests/unit/io/threading/__init__.py
tests/unit/io/threading/primitives.py
phyllo-0.2.0.dist-info/LICENSE
phyllo-0.2.0.dist-info/METADATA
phyllo-0.2.0.dist-info/WHEEL
phyllo-0.2.0.dist-info/top_level.txt
phyllo-0.2.0.dist-info/RECORD
